gllm_core.cpython-313-x86_64-linux-gnu.so
gllm_core.pyi
gllm_core/__init__.pyi
gllm_core/constants.pyi
gllm_core/adapters/__init__.pyi
gllm_core/adapters/tool/__init__.pyi
gllm_core/adapters/tool/google_adk.pyi
gllm_core/adapters/tool/langchain.pyi
gllm_core/event/__init__.pyi
gllm_core/event/event_emitter.pyi
gllm_core/event/messenger.pyi
gllm_core/event/handler/__init__.pyi
gllm_core/event/handler/console_event_handler.pyi
gllm_core/event/handler/event_handler.pyi
gllm_core/event/handler/print_event_handler.pyi
gllm_core/event/handler/stream_event_handler.pyi
gllm_core/event/hook/__init__.pyi
gllm_core/event/hook/event_hook.pyi
gllm_core/event/hook/json_stringify_event_hook.pyi
gllm_core/schema/__init__.pyi
gllm_core/schema/chunk.pyi
gllm_core/schema/component.pyi
gllm_core/schema/event.pyi
gllm_core/schema/graph.pyi
gllm_core/schema/schema_generator.pyi
gllm_core/schema/tool.pyi
gllm_core/utils/__init__.pyi
gllm_core/utils/analyzer.pyi
gllm_core/utils/binary_handler_factory.pyi
gllm_core/utils/chunk_metadata_merger.pyi
gllm_core/utils/concurrency.pyi
gllm_core/utils/event_formatter.pyi
gllm_core/utils/google_sheets.pyi
gllm_core/utils/imports.pyi
gllm_core/utils/logger_manager.pyi
gllm_core/utils/main_method_resolver.pyi
gllm_core/utils/merger_method.pyi
gllm_core/utils/repr.pyi
gllm_core/utils/retry.pyi
gllm_core/utils/similarity.pyi
gllm_core/utils/validation.pyi
gllm_core.build/.gitignore
gllm_core_binary-0.4.14.dist-info/METADATA
gllm_core_binary-0.4.14.dist-info/WHEEL
gllm_core_binary-0.4.14.dist-info/top_level.txt
gllm_core_binary-0.4.14.dist-info/RECORD
