Metadata-Version: 2.2
Name: gllm-core-binary
Version: 0.4.14
Summary: A library containing core components for Gen AI applications.
Author-email: Dimitrij Ray <dimitrij.ray@gdplabs.id>, Henry Wicaksono <henry.wicaksono@gdplabs.id>, Resti Febriana <resti.febriana@gdplabs.id>
Requires-Python: <3.14,>=3.11
Requires-Dist: anyio<5.0.0,>=4.10.0
Requires-Dist: deprecation<3.0.0,>=2.1.0
Requires-Dist: google<4.0.0,>=3.0.0
Requires-Dist: google-auth<3.0.0,>=2.38.0
Requires-Dist: gspread<7.0.0,>=6.1.4
Requires-Dist: numpy<2.0.0,>=1.26; python_version < "3.12"
Requires-Dist: numpy<3.0.0,>=1.26; python_version >= "3.12" and python_version < "3.13"
Requires-Dist: numpy<3.0.0,>=2.2; python_version >= "3.13"
Requires-Dist: pydantic<3.0.0,>=2.11.4
Requires-Dist: python-json-logger<4.0.0,>=3.3.0
Requires-Dist: rich<15.0.0,>=14.1.0
Requires-Dist: scipy<2.0.0,>=1.15.1
Provides-Extra: dev
Requires-Dist: coverage<8.0.0,>=7.4.4; extra == "dev"
Requires-Dist: mypy<2.0.0,>=1.15.0; extra == "dev"
Requires-Dist: pre-commit<4.0.0,>=3.7.0; extra == "dev"
Requires-Dist: pytest<9.0.0,>=8.1.1; extra == "dev"
Requires-Dist: pytest-asyncio<1.0.0,>=0.23.6; extra == "dev"
Requires-Dist: pytest-cov<6.0.0,>=5.0.0; extra == "dev"
Requires-Dist: ruff<1.0.0,>=0.6.7; extra == "dev"
Provides-Extra: langchain
Requires-Dist: langchain-core<1.0.0,>=0.3.0; extra == "langchain"
Provides-Extra: google-adk
Requires-Dist: google-adk<2.0.0,>=1.0.0; extra == "google-adk"
Requires-Dist: starlette<1.0.0,>=0.49.0; extra == "google-adk"
